ibm_service_validator/__init__.py
ibm_service_validator/cli/__init__.py
ibm_service_validator/cli/process_config.py
ibm_service_validator/cli/handlers/__init__.py
ibm_service_validator/cli/handlers/output_handler.py
ibm_service_validator/handbook_rules/__init__.py
ibm_service_validator/handbook_rules/add_case_rules/__init__.py
ibm_service_validator/handbook_rules/add_case_rules/get_with_request_body.py
ibm_service_validator/handbook_rules/add_case_rules/invalid_accept_header.py
ibm_service_validator/handbook_rules/add_case_rules/invalid_request_content_type.py
ibm_service_validator/handbook_rules/general_rules/__init__.py
ibm_service_validator/handbook_rules/general_rules/header_rules.py
ibm_service_validator/handbook_rules/general_rules/status_code_rules.py
ibm_service_validator-0.5.0.dist-info/LICENSE
ibm_service_validator-0.5.0.dist-info/METADATA
ibm_service_validator-0.5.0.dist-info/WHEEL
ibm_service_validator-0.5.0.dist-info/entry_points.txt
ibm_service_validator-0.5.0.dist-info/top_level.txt
ibm_service_validator-0.5.0.dist-info/RECORD
