Metadata-Version: 2.1
Name: ibm-service-validator
Version: 0.5.0
Summary: Python package, Schemathesis, extended to include IBM API Handbook validation.
Home-page: https://github.com/IBM/service-validator
Author-email: devexdev@us.ibm.com
License: Apache 2.0
Platform: UNKNOWN
Classifier: Programming Language :: Python :: 3
Classifier: Operating System :: OS Independent
Requires-Python: >=3.6
Requires-Dist: click
Requires-Dist: ibm-cloud-sdk-core
Requires-Dist: pyyaml
Requires-Dist: schemathesis
